{"P6": {"labels": ["papers"], "postTitle": "\u3010\u8bba\u6587\u6574\u7406\u3011Instance-level Control for Image Generation", "postUrl": "post/%E3%80%90-lun-wen-zheng-li-%E3%80%91Instance-level%20Control%20for%20Image%20Generation.html", "createdDate": "2024-10-24", "dateLabelColor": "#bc4c00"}, "P5": {"labels": ["papers"], "postTitle": "\u3010\u8bba\u6587\u9605\u8bfb\u3011Janus: Decoupling Visual Encoding for Unified Multimodal Understanding and Generation", "postUrl": "post/%E3%80%90-lun-wen-yue-du-%E3%80%91Janus-%20Decoupling%20Visual%20Encoding%20for%20Unified%20Multimodal%20Understanding%20and%20Generation.html", "createdDate": "2024-10-23", "dateLabelColor": "#bc4c00"}, "P4": {"labels": ["papers"], "postTitle": "\u3010\u8bba\u6587\u9605\u8bfb\u3011MONOFORMER: ONE TRANSFORMER FOR BOTH DIFFUSION AND AUTOREGRESSION", "postUrl": "post/%E3%80%90-lun-wen-yue-du-%E3%80%91MONOFORMER-%20ONE%20TRANSFORMER%20FOR%20BOTH%20DIFFUSION%20AND%20AUTOREGRESSION.html", "createdDate": "2024-10-16", "dateLabelColor": "#bc4c00"}, "P3": {"labels": ["papers"], "postTitle": "\u3010\u8bba\u6587\u9605\u8bfb\u3011Transfusion: Predict the Next Token and Diffuse Images with One Multi-Modal Model", "postUrl": "post/%E3%80%90-lun-wen-yue-du-%E3%80%91Transfusion-%20Predict%20the%20Next%20Token%20and%20Diffuse%20Images%20with%20One%20Multi-Modal%20Model.html", "createdDate": "2024-09-19", "dateLabelColor": "#bc4c00"}, "P2": {"labels": ["papers"], "postTitle": "\u3010\u8bba\u6587\u9605\u8bfb\u3011Show-o: ONE SINGLE TRANSFORMER TO UNIFY MULTIMODAL UNDERSTANDING AND GENERATION", "postUrl": "post/%E3%80%90-lun-wen-yue-du-%E3%80%91Show-o-%20ONE%20SINGLE%20TRANSFORMER%20TO%20UNIFY%20MULTIMODAL%20UNDERSTANDING%20AND%20GENERATION.html", "createdDate": "2024-09-18", "dateLabelColor": "#bc4c00"}, "P1": {"labels": ["code"], "postTitle": "StableDiffusion3\u4ee3\u7801\u5206\u6790", "postUrl": "post/StableDiffusion3-dai-ma-fen-xi.html", "createdDate": "2024-09-14", "dateLabelColor": "#bc4c00"}, "labelColorDict": {"bug": "#d73a4a", "code": "#5F34A5", "documentation": "#0075ca", "duplicate": "#cfd3d7", "enhancement": "#a2eeef", "good first issue": "#7057ff", "help wanted": "#008672", "invalid": "#e4e669", "papers": "#fbca04", "question": "#d876e3", "wontfix": "#ffffff"}}